[{"app_id":"6748812156916c433a3dfef4","country":"AU","date":"2026-01-19T00:00:00Z","android_revenue":4310,"unified_units":0,"unified_revenue":4310},{"app_id":"6748812156916c433a3dfef4","country":"CA","date":"2026-01-19T00:00:00Z","android_revenue":1506,"unified_units":0,"unified_revenue":1506},{"app_id":"6748812156916c433a3dfef4","country":"CN","date":"2026-01-19T00:00:00Z","iphone_units":20902,"iphone_revenue":104865557,"unified_units":20902,"unified_revenue":104865557},{"app_id":"6748812156916c433a3dfef4","country":"HK","date":"2026-01-19T00:00:00Z","android_units":11,"android_revenue":410374,"iphone_units":22,"iphone_revenue":275759,"unified_units":33,"unified_revenue":686133},{"app_id":"6748812156916c433a3dfef4","country":"ID","date":"2026-01-19T00:00:00Z","android_units":574,"android_revenue":85876,"iphone_revenue":142249,"unified_units":574,"unified_revenue":228125},{"app_id":"6748812156916c433a3dfef4","country":"JP","date":"2026-01-19T00:00:00Z","android_revenue":223580,"iphone_revenue":320251,"unified_units":0,"unified_revenue":543831},{"app_id":"6748812156916c433a3dfef4","country":"KH","date":"2026-01-19T00:00:00Z","android_revenue":4709,"iphone_revenue":709,"unified_units":0,"unified_revenue":5418},{"app_id":"6748812156916c433a3dfef4","country":"KR","date":"2026-01-19T00:00:00Z","android_units":13,"android_revenue":812420,"iphone_revenue":59376,"unified_units":13,"unified_revenue":871796},{"app_id":"6748812156916c433a3dfef4","country":"LY","date":"2026-01-19T00:00:00Z","unified_units":0,"unified_revenue":0},{"app_id":"6748812156916c433a3dfef4","country":"MM","date":"2026-01-19T00:00:00Z","android_revenue":64782,"unified_units":0,"unified_revenue":64782},{"app_id":"6748812156916c433a3dfef4","country":"MO","date":"2026-01-19T00:00:00Z","android_revenue":2705,"iphone_revenue":18481,"unified_units":0,"unified_revenue":21186},{"app_id":"6748812156916c433a3dfef4","country":"MY","date":"2026-01-19T00:00:00Z","android_revenue":133122,"iphone_revenue":118151,"unified_units":0,"unified_revenue":251273},{"app_id":"6748812156916c433a3dfef4","country":"PH","date":"2026-01-19T00:00:00Z","android_units":1049,"android_revenue":1638,"unified_units":1049,"unified_revenue":1638},{"app_id":"6748812156916c433a3dfef4","country":"SG","date":"2026-01-19T00:00:00Z","android_revenue":138201,"iphone_units":1,"iphone_revenue":58178,"unified_units":1,"unified_revenue":196379},{"app_id":"6748812156916c433a3dfef4","country":"TH","date":"2026-01-19T00:00:00Z","android_revenue":5398,"iphone_units":2,"iphone_revenue":27451,"unified_units":2,"unified_revenue":32849},{"app_id":"6748812156916c433a3dfef4","country":"TW","date":"2026-01-19T00:00:00Z","android_units":34,"android_revenue":890005,"iphone_units":23,"iphone_revenue":1948812,"unified_units":57,"unified_revenue":2838817},{"app_id":"6748812156916c433a3dfef4","country":"US","date":"2026-01-19T00:00:00Z","android_revenue":162309,"unified_units":0,"unified_revenue":162309},{"app_id":"6748812156916c433a3dfef4","country":"AU","date":"2026-01-26T00:00:00Z","android_revenue":1874,"unified_units":0,"unified_revenue":1874},{"app_id":"6748812156916c433a3dfef4","country":"CA","date":"2026-01-26T00:00:00Z","unified_units":0,"unified_revenue":0},{"app_id":"6748812156916c433a3dfef4","country":"CN","date":"2026-01-26T00:00:00Z","iphone_units":7407,"iphone_revenue":36569034,"unified_units":7407,"unified_revenue":36569034},{"app_id":"6748812156916c433a3dfef4","country":"HK","date":"2026-01-26T00:00:00Z","android_units":6,"android_revenue":173439,"iphone_units":22,"iphone_revenue":69098,"unified_units":28,"unified_revenue":242537},{"app_id":"6748812156916c433a3dfef4","country":"ID","date":"2026-01-26T00:00:00Z","android_units":768,"android_revenue":37911,"iphone_revenue":50397,"unified_units":768,"unified_revenue":88308},{"app_id":"6748812156916c433a3dfef4","country":"JP","date":"2026-01-26T00:00:00Z","android_revenue":84656,"iphone_revenue":117039,"unified_units":0,"unified_revenue":201695},{"app_id":"6748812156916c433a3dfef4","country":"KH","date":"2026-01-26T00:00:00Z","android_revenue":226,"iphone_revenue":348,"unified_units":0,"unified_revenue":574},{"app_id":"6748812156916c433a3dfef4","country":"KR","date":"2026-01-26T00:00:00Z","android_units":6,"android_revenue":365723,"iphone_revenue":42903,"unified_units":6,"unified_revenue":408626},{"app_id":"6748812156916c433a3dfef4","country":"MM","date":"2026-01-26T00:00:00Z","android_revenue":44331,"unified_units":0,"unified_revenue":44331},{"app_id":"6748812156916c433a3dfef4","country":"MO","date":"2026-01-26T00:00:00Z","android_revenue":1089,"iphone_revenue":1895,"unified_units":0,"unified_revenue":2984},{"app_id":"6748812156916c433a3dfef4","country":"MY","date":"2026-01-26T00:00:00Z","android_revenue":71138,"iphone_revenue":35474,"unified_units":0,"unified_revenue":106612},{"app_id":"6748812156916c433a3dfef4","country":"PH","date":"2026-01-26T00:00:00Z","android_units":1400,"android_revenue":723,"unified_units":1400,"unified_revenue":723},{"app_id":"6748812156916c433a3dfef4","country":"SG","date":"2026-01-26T00:00:00Z","android_revenue":63273,"iphone_units":1,"iphone_revenue":15440,"unified_units":1,"unified_revenue":78713},{"app_id":"6748812156916c433a3dfef4","country":"TH","date":"2026-01-26T00:00:00Z","android_revenue":2461,"iphone_revenue":8943,"unified_units":0,"unified_revenue":11404},{"app_id":"6748812156916c433a3dfef4","country":"TW","date":"2026-01-26T00:00:00Z","android_units":10,"android_revenue":380342,"iphone_units":6,"iphone_revenue":430935,"unified_units":16,"unified_revenue":811277},{"app_id":"6748812156916c433a3dfef4","country":"US","date":"2026-01-26T00:00:00Z","android_revenue":46529,"unified_units":0,"unified_revenue":46529}]